tsp_heuristics/__init__.py
tsp_heuristics/heuristics/__init__.py
tsp_heuristics/heuristics/grasp.py
tsp_heuristics/heuristics/local_search.py
tsp_heuristics/heuristics/nn.py
tsp_heuristics/heuristics/utils.py
tsp_heuristics/utils/__init__.py
tsp_heuristics/utils/plot.py
tsp_heuristics/utils/readfile.py
tsp_heuristics-0.2.5.dist-info/LICENSE
tsp_heuristics-0.2.5.dist-info/WHEEL
tsp_heuristics-0.2.5.dist-info/METADATA
tsp_heuristics-0.2.5.dist-info/RECORD
